bayescnn/__init__.py
bayescnn/core/__init__.py
bayescnn/core/bayesian.py
bayescnn/layers/__init__.py
bayescnn/layers/conv.py
bayescnn/layers/linear.py
bayescnn/loss/__init__.py
bayescnn/loss/loss.py
bayescnn/models/__init__.py
bayescnn/models/bayes_simple_conv.py
bayescnn/models/bayes_unet.py
bayescnn-1.0.0.dist-info/METADATA
bayescnn-1.0.0.dist-info/WHEEL
bayescnn-1.0.0.dist-info/RECORD
