Metadata-Version: 2.3
Name: bayescnn
Version: 1.0.0
Summary: Add your description here
Author-email: Samuel Ball <stmball@gmail.com>
Requires-Python: >=3.8
Requires-Dist: jupyter>=1.1.1
Requires-Dist: matplotlib>=3.10.1
Requires-Dist: numpy>=2.2.4
Requires-Dist: rich>=13.9.4
Requires-Dist: scikit-learn>=1.6.1
Requires-Dist: torch-summary>=1.4.5
Requires-Dist: torch>=2.6.0
Requires-Dist: torchvision>=0.21.0
Requires-Dist: unet>=0.8.1
